odoo/addons/sale_delivery_date/README.rst
odoo/addons/sale_delivery_date/__init__.py
odoo/addons/sale_delivery_date/__manifest__.py
odoo/addons/sale_delivery_date/hooks.py
odoo/addons/sale_delivery_date/i18n/de.po
odoo/addons/sale_delivery_date/i18n/fr_CH.po
odoo/addons/sale_delivery_date/i18n/it.po
odoo/addons/sale_delivery_date/i18n/sale_delivery_date.pot
odoo/addons/sale_delivery_date/models/__init__.py
odoo/addons/sale_delivery_date/models/cutoff_time_mixin.py
odoo/addons/sale_delivery_date/models/res_partner.py
odoo/addons/sale_delivery_date/models/sale_order.py
odoo/addons/sale_delivery_date/models/sale_order_line.py
odoo/addons/sale_delivery_date/models/stock_picking.py
odoo/addons/sale_delivery_date/models/stock_warehouse.py
odoo/addons/sale_delivery_date/readme/CONTRIBUTORS.rst
odoo/addons/sale_delivery_date/readme/DESCRIPTION.rst
odoo/addons/sale_delivery_date/readme/ROADMAP.rst
odoo/addons/sale_delivery_date/readme/USAGE.rst
odoo/addons/sale_delivery_date/reports/sale_order.xml
odoo/addons/sale_delivery_date/reports/stock_picking.xml
odoo/addons/sale_delivery_date/static/description/icon.png
odoo/addons/sale_delivery_date/static/description/index.html
odoo/addons/sale_delivery_date/tests/__init__.py
odoo/addons/sale_delivery_date/tests/common.py
odoo/addons/sale_delivery_date/tests/test_delivery_date_in_the_past.py
odoo/addons/sale_delivery_date/tests/test_integration.py
odoo/addons/sale_delivery_date/tests/test_reports.py
odoo/addons/sale_delivery_date/tests/test_sale_cutoff_time_delivery.py
odoo/addons/sale_delivery_date/tests/test_sale_partner_cutoff_delivery_window.py
odoo/addons/sale_delivery_date/tests/test_sale_partner_delivery_window.py
odoo/addons/sale_delivery_date/tests/test_sale_warehouse_calendar.py
odoo/addons/sale_delivery_date/views/res_partner.xml
odoo/addons/sale_delivery_date/views/stock_picking.xml
odoo/addons/sale_delivery_date/views/stock_warehouse.xml
odoo14_addon_sale_delivery_date-14.0.1.1.0.dist-info/METADATA
odoo14_addon_sale_delivery_date-14.0.1.1.0.dist-info/WHEEL
odoo14_addon_sale_delivery_date-14.0.1.1.0.dist-info/top_level.txt
odoo14_addon_sale_delivery_date-14.0.1.1.0.dist-info/RECORD
